{
    "_id": "68efc01705fb2137056fb725",
    "url_name": "thornbak",
    "group": "primary",
    "riven_type": "rifle",
    "disposition": 1,
    "mastery_level": 0,
    "game_ref": {
        "uniq_name": "/Lotus/Weapons/Tenno/LongGuns/TnModQuestRifle/TnModQuestRifleWeapon"
    },
    "i18n": {
        "en": {
            "item_name": "Thornbak",
            "wiki_link": null,
            "icon": "items/images/en/thornbak.fd909dd625865ed8fdeadc98b8a86c4e.webp",
            "thumb": "items/images/en/thumbs/thornbak.fd909dd625865ed8fdeadc98b8a86c4e.128x128.webp"
        },
        "ru": {
            "item_name": "Торнбак",
            "wiki_link": null,
            "icon": "items/images/en/thornbak.fd909dd625865ed8fdeadc98b8a86c4e.webp",
            "thumb": "items/images/en/thumbs/thornbak.fd909dd625865ed8fdeadc98b8a86c4e.128x128.webp"
        },
        "ko": {
            "item_name": "쏜바크",
            "wiki_link": null,
            "icon": "items/images/en/thornbak.fd909dd625865ed8fdeadc98b8a86c4e.webp",
            "thumb": "items/images/en/thumbs/thornbak.fd909dd625865ed8fdeadc98b8a86c4e.128x128.webp"
        },
        "de": {
            "item_name": "Thornbak",
            "wiki_link": null,
            "icon": "items/images/en/thornbak.fd909dd625865ed8fdeadc98b8a86c4e.webp",
            "thumb": "items/images/en/thumbs/thornbak.fd909dd625865ed8fdeadc98b8a86c4e.128x128.webp"
        },
        "fr": {
            "item_name": "Thornbak",
            "wiki_link": null,
            "icon": "items/images/en/thornbak.fd909dd625865ed8fdeadc98b8a86c4e.webp",
            "thumb": "items/images/en/thumbs/thornbak.fd909dd625865ed8fdeadc98b8a86c4e.128x128.webp"
        },
        "pt": {
            "item_name": "Thornbak",
            "wiki_link": null,
            "icon": "items/images/en/thornbak.fd909dd625865ed8fdeadc98b8a86c4e.webp",
            "thumb": "items/images/en/thumbs/thornbak.fd909dd625865ed8fdeadc98b8a86c4e.128x128.webp"
        },
        "zh-hans": {
            "item_name": "棘背",
            "wiki_link": null,
            "icon": "items/images/en/thornbak.fd909dd625865ed8fdeadc98b8a86c4e.webp",
            "thumb": "items/images/en/thumbs/thornbak.fd909dd625865ed8fdeadc98b8a86c4e.128x128.webp"
        },
        "zh-hant": {
            "item_name": "刺棘",
            "wiki_link": null,
            "icon": "items/images/en/thornbak.fd909dd625865ed8fdeadc98b8a86c4e.webp",
            "thumb": "items/images/en/thumbs/thornbak.fd909dd625865ed8fdeadc98b8a86c4e.128x128.webp"
        },
        "es": {
            "item_name": "Thornbak",
            "wiki_link": null,
            "icon": "items/images/en/thornbak.fd909dd625865ed8fdeadc98b8a86c4e.webp",
            "thumb": "items/images/en/thumbs/thornbak.fd909dd625865ed8fdeadc98b8a86c4e.128x128.webp"
        },
        "it": {
            "item_name": "Thornbak",
            "wiki_link": null,
            "icon": "items/images/en/thornbak.fd909dd625865ed8fdeadc98b8a86c4e.webp",
            "thumb": "items/images/en/thumbs/thornbak.fd909dd625865ed8fdeadc98b8a86c4e.128x128.webp"
        },
        "pl": {
            "item_name": "Thornbak",
            "wiki_link": null,
            "icon": "items/images/en/thornbak.fd909dd625865ed8fdeadc98b8a86c4e.webp",
            "thumb": "items/images/en/thumbs/thornbak.fd909dd625865ed8fdeadc98b8a86c4e.128x128.webp"
        },
        "uk": {
            "item_name": "Шиповиця",
            "wiki_link": null,
            "icon": "items/images/en/thornbak.fd909dd625865ed8fdeadc98b8a86c4e.webp",
            "thumb": "items/images/en/thumbs/thornbak.fd909dd625865ed8fdeadc98b8a86c4e.128x128.webp"
        }
    }
}