{
    "_id": "68adcffe731e63abe79a5d10",
    "tags": [
        "warframe",
        "prime",
        "blueprint"
    ],
    "icon": "items/unknown.png",
    "thumb": "items/unknown.thumb.png",
    "sub_icon": "sub_icons/blueprint_128x128.png",
    "url_name": "caliban_prime_blueprint",
    "tradable": true,
    "game_ref": {
        "uniq_name": "/Lotus/Types/Recipes/WarframeRecipes/CalibanPrimeBlueprint"
    },
    "part_of_set": [
        "caliban_prime_blueprint",
        "caliban_prime_chassis_blueprint",
        "caliban_prime_neuroptics_blueprint",
        "caliban_prime_set",
        "caliban_prime_systems_blueprint"
    ],
    "set_root": false,
    "quantity_for_set": 1,
    "i18n": {
        "en": {
            "item_name": "Caliban Prime Blueprint",
            "description": "Forged in celebration of the all-too-brief peace between the Orokin and Sentients, Caliban Prime is a true collaborative masterpiece. The heir of twin kingdoms arises in royal gold.",
            "wiki_link": null,
            "icon": "items/unknown.png"
        },
        "ru": {
            "item_name": "Калибан Прайм (Чертеж)",
            "description": "Выкованный в честь недолговечного мира между Орокин и Владеющими Разумом, варфрейм «Калибан Прайм» — настоящий шедевр, созданный их совместными усилиями. Наследник королевств-близнецов восстаёт в королевской позолоте.",
            "wiki_link": null,
            "icon": "items/unknown.png"
        },
        "ko": {
            "item_name": "칼리반 프라임 설계도",
            "description": "오로킨과 센티언트 사이의 짧았던 평화를 기념하며 제작된 칼리반 프라임은 진정한 협업의 걸작품입니다. 센티언트와 오로킨, 두 왕국의 후계자가 왕실의 황금 속에서 탄생하였습니다.",
            "wiki_link": null,
            "icon": "items/unknown.png"
        },
        "de": {
            "item_name": "Caliban Prime Blaupause",
            "description": "Geschmiedet zur Feier des viel zu kurzen Friedens zwischen den Orokin und den Sentients, ist Caliban Prime ein wahres Meisterwerk dieser Zusammenarbeit. Der Erbe eines Zwillingskönigreichs erhebt sich königlichem Gold.",
            "wiki_link": null,
            "icon": "items/unknown.png"
        },
        "fr": {
            "item_name": "Caliban Prime (Schéma)",
            "description": "Forgé pour célébrer la paix bien trop brève entre les Orokins et les Sentients, Caliban Prime est un véritable chef-d'œuvre collaboratif. L'héritier des royaumes jumeaux s'élève dans une tenue dorée royale.",
            "wiki_link": null,
            "icon": "items/unknown.png"
        },
        "pt": {
            "item_name": "Caliban Prime (Diagrama)",
            "description": "Forjado em celebração à breve paz entre os Orokin e os Sentients, o Caliban Prime é uma verdadeira obra-prima colaborativa. O herdeiro dos reinos gêmeos resplandece em ouro real.",
            "wiki_link": null,
            "icon": "items/unknown.png"
        },
        "zh-hans": {
            "item_name": "Caliban Prime 蓝图",
            "description": "Caliban Prime 是为了庆祝奥罗金与 Sentient 之间短暂的和平而打造的，堪称真正的合璧杰作。双生王国的继承者，身披皇家之金崛起。",
            "wiki_link": null,
            "icon": "items/unknown.png"
        },
        "zh-hant": {
            "item_name": "Caliban Prime 藍圖",
            "description": "為慶祝 Orokin 與 Sentient 之間短暫而珍貴的和平而鍛造，Caliban Prime 正是攜手合作下的傑作。雙界之裔以皇金之姿崛起於世。",
            "wiki_link": null,
            "icon": "items/unknown.png"
        },
        "es": {
            "item_name": "Plano de Caliban Prime",
            "description": "Caliban Prime, forjado para celebrar la breve paz entre los orokin y los conscientes, es una auténtica obra maestra de colaboración. El heredero de los reinos gemelos se levanta cubierto de un majestuoso dorado imperial.",
            "wiki_link": null,
            "icon": "items/unknown.png"
        },
        "it": {
            "item_name": "Caliban Prime (Schema)",
            "description": "Forgiato per celebrare la pace fin troppo breve tra Orokin e Sentient, Caliban Prime è un vero capolavoro frutto di una collaborazione. L'erede dei regni gemelli sorge nell'oro reale.",
            "wiki_link": null,
            "icon": "items/unknown.png"
        },
        "pl": {
            "item_name": "Caliban Prime - Schemat",
            "description": "Stworzony na cześć krótkotrwałego rozejmu między Orokin a Świadomymi, Caliban Prime stanowi prawdziwe arcydzieło współpracy cywilizacji. Spadkobierca bliźniaczych królestw powstaje, spowity królewskim złotem.",
            "wiki_link": null,
            "icon": "items/unknown.png"
        },
        "uk": {
            "item_name": "Калібан-Прайм (кресленик)",
            "description": "Калібан-прайм — шедевральний результат спільної праці, створений, щоб ушанувати короткочасний мир між орокінами та свідомими. Спадкоємець двох світів сяятиме в королівському золоті.",
            "wiki_link": null,
            "icon": "items/unknown.png"
        }
    },
    "mastery_level": 0,
    "ducats": 45,
    "trading_tax": 2000
}