{
    "_id": "69765a057b65a4e83d4ab4ae",
    "tags": [
        "arcane_enhancement"
    ],
    "icon": "items/images/en/zid-an-sek-eel.8bc9e9fa897d0231cdeca3f6d8645e66.webp",
    "thumb": "items/images/en/thumbs/zid-an-sek-eel.8bc9e9fa897d0231cdeca3f6d8645e66.128x128.webp",
    "url_name": "zid-an-sek-eel",
    "tradable": true,
    "game_ref": {
        "uniq_name": "/Lotus/Upgrades/CosmeticEnhancers/Antiques/UltimateInvisibilty"
    },
    "i18n": {
        "en": {
            "item_name": "Zid-an Sek-eel",
            "description": "Gain invisibility for 30s after activating Tauron Strike",
            "wiki_link": null,
            "icon": "items/images/en/zid-an-sek-eel.8bc9e9fa897d0231cdeca3f6d8645e66.webp",
            "thumb": "items/images/en/thumbs/zid-an-sek-eel.8bc9e9fa897d0231cdeca3f6d8645e66.128x128.webp"
        },
        "ru": {
            "item_name": "Зид-ан Сек-ил",
            "description": "Получите невидимость на 30 с после активации Удара Таурона",
            "wiki_link": null,
            "icon": "items/images/en/zid-an-sek-eel.8bc9e9fa897d0231cdeca3f6d8645e66.webp",
            "thumb": "items/images/en/thumbs/zid-an-sek-eel.8bc9e9fa897d0231cdeca3f6d8645e66.128x128.webp"
        },
        "ko": {
            "item_name": "지드-안 세크-일",
            "description": "타우론 일격 활성화 후 30초 동안 은신 효과 획득",
            "wiki_link": null,
            "icon": "items/images/en/zid-an-sek-eel.8bc9e9fa897d0231cdeca3f6d8645e66.webp",
            "thumb": "items/images/en/thumbs/zid-an-sek-eel.8bc9e9fa897d0231cdeca3f6d8645e66.128x128.webp"
        },
        "de": {
            "item_name": "Zid-an Sek-eel",
            "description": "Gewährt nach Aktivierung von Tauron-Schlag für 30 s Unsichtbarkeit",
            "wiki_link": null,
            "icon": "items/images/en/zid-an-sek-eel.8bc9e9fa897d0231cdeca3f6d8645e66.webp",
            "thumb": "items/images/en/thumbs/zid-an-sek-eel.8bc9e9fa897d0231cdeca3f6d8645e66.128x128.webp"
        },
        "fr": {
            "item_name": "Zid-an Sek-eel",
            "description": "Vous devenez invisible pendant 30s après avoir activé la Frappe Tauron",
            "wiki_link": null,
            "icon": "items/images/en/zid-an-sek-eel.8bc9e9fa897d0231cdeca3f6d8645e66.webp",
            "thumb": "items/images/en/thumbs/zid-an-sek-eel.8bc9e9fa897d0231cdeca3f6d8645e66.128x128.webp"
        },
        "pt": {
            "item_name": "Zid-An Sek-Eel",
            "description": "Fornecerá invisibilidade por 30s após ativar a Ofensiva Tauron.",
            "wiki_link": null,
            "icon": "items/images/en/zid-an-sek-eel.8bc9e9fa897d0231cdeca3f6d8645e66.webp",
            "thumb": "items/images/en/thumbs/zid-an-sek-eel.8bc9e9fa897d0231cdeca3f6d8645e66.128x128.webp"
        },
        "zh-hans": {
            "item_name": "齐塞",
            "description": "激活 Tauron 打击后获得隐身效果，持续 30 秒",
            "wiki_link": null,
            "icon": "items/images/en/zid-an-sek-eel.8bc9e9fa897d0231cdeca3f6d8645e66.webp",
            "thumb": "items/images/en/thumbs/zid-an-sek-eel.8bc9e9fa897d0231cdeca3f6d8645e66.128x128.webp"
        },
        "zh-hant": {
            "item_name": "茲賽",
            "description": "啟用 Tauron 打擊後，進入隱形狀態，持續 30 秒",
            "wiki_link": null,
            "icon": "items/images/en/zid-an-sek-eel.8bc9e9fa897d0231cdeca3f6d8645e66.webp",
            "thumb": "items/images/en/thumbs/zid-an-sek-eel.8bc9e9fa897d0231cdeca3f6d8645e66.128x128.webp"
        },
        "es": {
            "item_name": "Zid-an Sek-eel",
            "description": "Obtén invisibilidad por 30 s después de activar un Ataque Tauron",
            "wiki_link": null,
            "icon": "items/images/en/zid-an-sek-eel.8bc9e9fa897d0231cdeca3f6d8645e66.webp",
            "thumb": "items/images/en/thumbs/zid-an-sek-eel.8bc9e9fa897d0231cdeca3f6d8645e66.128x128.webp"
        },
        "it": {
            "item_name": "Zid-an Sek-eel",
            "description": "Ottieni invisibilità per 30s dopo aver attivato il Colpo Tauron",
            "wiki_link": null,
            "icon": "items/images/en/zid-an-sek-eel.8bc9e9fa897d0231cdeca3f6d8645e66.webp",
            "thumb": "items/images/en/thumbs/zid-an-sek-eel.8bc9e9fa897d0231cdeca3f6d8645e66.128x128.webp"
        },
        "pl": {
            "item_name": "Zid-an Sek-eel",
            "description": "Zyskaj 30 s niewidzialności po użyciu Ataku Tauronu",
            "wiki_link": null,
            "icon": "items/images/en/zid-an-sek-eel.8bc9e9fa897d0231cdeca3f6d8645e66.webp",
            "thumb": "items/images/en/thumbs/zid-an-sek-eel.8bc9e9fa897d0231cdeca3f6d8645e66.128x128.webp"
        },
        "uk": {
            "item_name": "Зід-ан Сек-іл",
            "description": "30 с невидимості після застосування тауронського удару",
            "wiki_link": null,
            "icon": "items/images/en/zid-an-sek-eel.8bc9e9fa897d0231cdeca3f6d8645e66.webp",
            "thumb": "items/images/en/thumbs/zid-an-sek-eel.8bc9e9fa897d0231cdeca3f6d8645e66.128x128.webp"
        }
    },
    "max_rank": 5,
    "trading_tax": 4000
}